whatsapie/__init__.py
whatsapie/constants.py
whatsapie/errors.py
whatsapie/ext/__init__.py
whatsapie/ext/message/__init__.py
whatsapie/ext/message/group.py
whatsapie/ext/message/location.py
whatsapie/ext/message/media.py
whatsapie/ext/message/message.py
whatsapie/ext/message/text.py
whatsapie/schema_generator/__init__.py
whatsapie/schema_generator/location_schema.py
whatsapie/schema_generator/media_schema.py
whatsapie/schema_generator/text_schema.py
whatsapie-0.2.0.dist-info/LICENSE.txt
whatsapie-0.2.0.dist-info/WHEEL
whatsapie-0.2.0.dist-info/METADATA
whatsapie-0.2.0.dist-info/RECORD
