Metadata-Version: 2.1
Name: whatsapie
Version: 0.2.0
Summary: Unofficial Python wrapper for Meta's whatsapp cloud API
Home-page: https://advrxh.github.io/whatsapie
License: MIT
Keywords: whatsapp,cloud,api,python,wrapper
Author: Aadil Varsh
Author-email: aadilvarshofficial@gmail.com
Requires-Python: >=3.10,<4.0
Classifier: License :: OSI Approved :: MIT License
Classifier: Programming Language :: Python :: 3
Classifier: Programming Language :: Python :: 3.10
Requires-Dist: httpx (>=0.23.0,<0.24.0)
Requires-Dist: loguru (>=0.6.0,<0.7.0)
Project-URL: Repository, https://github.com/advrxh/whatsapie
